{
	"name": "github",
	"api_url": "https://api.github.com/",
	"url": "https://github.com/login/oauth",
	"oauth2": {
		"authorize": "/authorize",
		"access_token": "/access_token",
		"request": {
			"query": {
				"access_token": "{{token}}"
			}
		},
		"parameters": {
			"client_id": "string",
			"client_secret": "string",
			"scope": {
				"type": "string",
				"separator": " ",
				"cardinality": "*",
				"values": {
					"user": "Read/write access to profile info only. Note: this scope includes user:email and user:follow.",
					"user:email": "Read access to a user’s email addresses.",
					"user:follow": "Access to follow or unfollow other users.",
					"public_repo": "Read/write access to public repos and organizations.",
					"repo": "Read/write access to public and private repos and organizations.",
					"repo:status": "Read/write access to public and private repository commit statuses. This scope is only necessary to grant other users or services access to private repository commit statuses without granting access to the code. The repo and public_repo scopes already include access to commit status for private and public repositories respectively.",
					"delete_repo": "Delete access to adminable repositories.",
					"notifications": "Read access to a user’s notifications. repo is accepted too.",
					"gist": "Write access to gists."
				}
			}
		}
	}
}